twrap/__init__.py
twrap/cli.py
twrap-1.0.0.dist-info/LICENSE
twrap-1.0.0.dist-info/METADATA
twrap-1.0.0.dist-info/WHEEL
twrap-1.0.0.dist-info/entry_points.txt
twrap-1.0.0.dist-info/RECORD
