Metadata-Version: 2.3
Name: twrap
Version: 1.0.0
Summary: A CLI tool to wrap text
License: MIT
Author: Mohammad Mohsen
Author-email: kuro.ece@gmail.com
Requires-Python: >=3.11
Classifier: Programming Language :: Python :: 3
Classifier: Operating System :: OS Independent
Classifier: Environment :: Console
